{
  "ny": [
    {
      "name": "Basketball",
      "img": "https://i.imgur.com/1ZQ3w9O.jpg",
      "slug": "basketball",
      "description": "The New York City Pride Basketball League is New York's first official LGBTQIA+ basketball league. The league provides an environment free of harassment and discrimination for members and friends of the LGBT community to play basketball and fulfill their athletic aspirations. Games are played at the Field House at Chelsea Piers.",
      "website": "https://www.pridebasketballnyc.org"
    }
  ],
  "la": [],
  "ftl": []
}
